cleo/__init__.py
cleo/_compat.py
cleo/_utils.py
cleo/application.py
cleo/color.py
cleo/commands/__init__.py
cleo/commands/base_command.py
cleo/commands/command.py
cleo/commands/completions/__init__.py
cleo/commands/completions/templates.py
cleo/commands/completions_command.py
cleo/commands/help_command.py
cleo/commands/list_command.py
cleo/cursor.py
cleo/descriptors/__init__.py
cleo/descriptors/application_description.py
cleo/descriptors/descriptor.py
cleo/descriptors/text_descriptor.py
cleo/events/__init__.py
cleo/events/console_command_event.py
cleo/events/console_error_event.py
cleo/events/console_event.py
cleo/events/console_events.py
cleo/events/console_signal_event.py
cleo/events/console_terminate_event.py
cleo/events/event.py
cleo/events/event_dispatcher.py
cleo/exceptions/__init__.py
cleo/formatters/__init__.py
cleo/formatters/formatter.py
cleo/formatters/style.py
cleo/formatters/style_stack.py
cleo/helpers.py
cleo/io/__init__.py
cleo/io/buffered_io.py
cleo/io/inputs/__init__.py
cleo/io/inputs/argument.py
cleo/io/inputs/argv_input.py
cleo/io/inputs/definition.py
cleo/io/inputs/input.py
cleo/io/inputs/option.py
cleo/io/inputs/string_input.py
cleo/io/inputs/token_parser.py
cleo/io/io.py
cleo/io/null_io.py
cleo/io/outputs/__init__.py
cleo/io/outputs/buffered_output.py
cleo/io/outputs/null_output.py
cleo/io/outputs/output.py
cleo/io/outputs/section_output.py
cleo/io/outputs/stream_output.py
cleo/loaders/__init__.py
cleo/loaders/command_loader.py
cleo/loaders/factory_command_loader.py
cleo/py.typed
cleo/terminal.py
cleo/testers/__init__.py
cleo/testers/application_tester.py
cleo/testers/command_tester.py
cleo/ui/__init__.py
cleo/ui/choice_question.py
cleo/ui/component.py
cleo/ui/confirmation_question.py
cleo/ui/exception_trace/__init__.py
cleo/ui/exception_trace/component.py
cleo/ui/exception_trace/frame.py
cleo/ui/exception_trace/frame_collection.py
cleo/ui/exception_trace/inspector.py
cleo/ui/progress_bar.py
cleo/ui/progress_indicator.py
cleo/ui/question.py
cleo-2.2.0.dist-info/LICENSE
cleo-2.2.0.dist-info/METADATA
cleo-2.2.0.dist-info/WHEEL
cleo-2.2.0.dist-info/RECORD
